terminal_wrapped/__init__.py
terminal_wrapped/__main__.py
terminal_wrapped/analyzer.py
terminal_wrapped/app.py
terminal_wrapped/screens/__init__.py
terminal_wrapped/screens/finale.py
terminal_wrapped/screens/splash.py
terminal_wrapped/screens/stats.py
terminal_wrapped/widgets/__init__.py
terminal_wrapped/widgets/cube.py
terminal_wrapped/widgets/gradient_bg.py
term_wrapped-0.1.1.dist-info/METADATA
term_wrapped-0.1.1.dist-info/WHEEL
term_wrapped-0.1.1.dist-info/entry_points.txt
term_wrapped-0.1.1.dist-info/RECORD
