Metadata-Version: 2.4
Name: term-wrapped
Version: 0.1.1
Summary: Your year in the terminal - a visual wrapped experience for shell commands
Project-URL: Homepage, https://github.com/SinaKhalili/term-wrapped
Project-URL: Repository, https://github.com/SinaKhalili/term-wrapped
Author: Sina
License: MIT
Keywords: cli,history,shell,statistics,terminal,wrapped
Classifier: Development Status :: 4 - Beta
Classifier: Environment :: Console
Classifier: Intended Audience :: Developers
Classifier: License :: OSI Approved :: MIT License
Classifier: Operating System :: OS Independent
Classifier: Programming Language :: Python :: 3
Classifier: Programming Language :: Python :: 3.11
Classifier: Programming Language :: Python :: 3.12
Classifier: Programming Language :: Python :: 3.13
Classifier: Topic :: Utilities
Requires-Python: >=3.11
Requires-Dist: rich>=14.0.0
Requires-Dist: textual>=1.0.0
